<Properties StartupConfiguration="{98FEE8C7-F58D-4574-9DCA-C4CE0D75F8F9}|Default">
  <MonoDevelop.Ide.Workbench ActiveDocument="App3/App3/teacherClassInfo.xaml.cs">
    <Files>
      <File FileName="App3/App3/QRcodeScanner.xaml" Line="7" Column="1" />
      <File FileName="App3/App3/QRcodeScanner.xaml.cs" />
      <File FileName="App3/App3/teacherClassInfo.xaml.cs" Line="126" Column="1" />
      <File FileName="App3/App3/NewClassPage.xaml.cs" />
      <File FileName="App3/App3/App.xaml.cs" />
      <File FileName="App3/App3/teacherClassInfo.xaml" />
      <File FileName="App3/App3/obj/Debug/netstandard2.0/teacherClassInfo.xaml.g.cs" />
    </Files>
  </MonoDevelop.Ide.Workbench>
  <MonoDevelop.Ide.ItemProperties.App3.Android PreferredExecutionTarget="Android.Android_Accelerated_Oreo" />
  <MonoDevelop.Ide.DebuggingService.PinnedWatches />
  <MonoDevelop.Ide.Workspace ActiveConfiguration="Debug" />
  <MonoDevelop.Ide.DebuggingService.Breakpoints>
    <BreakpointStore />
  </MonoDevelop.Ide.DebuggingService.Breakpoints>
  <MultiItemStartupConfigurations />
</Properties>